CHANGES.txt
LICENSE.txt
MANIFEST.in
README.txt
setup.cfg
setup.py
version.txt
examples/__init__.py
examples/example.ini
examples/example.mako
examples/sqlalchemy_orm_example.py
pyramid_restler/__init__.py
pyramid_restler/config.py
pyramid_restler/interfaces.py
pyramid_restler/model.py
pyramid_restler/tests.py
pyramid_restler/view.py
pyramid_restler.egg-info/PKG-INFO
pyramid_restler.egg-info/SOURCES.txt
pyramid_restler.egg-info/dependency_links.txt
pyramid_restler.egg-info/requires.txt
pyramid_restler.egg-info/top_level.txt