Metadata-Version: 1.1
Name: pyramid-restler
Version: 0.1a4
Summary: RESTful views for Pyramid
Home-page: https://bitbucket.org/wyatt/pyramid_restler
Author: Wyatt Lee Baldwin
Author-email: wyatt.lee.baldwin@gmail.com
License: UNKNOWN
Keywords: Web REST Pylons Pyramid
Platform: UNKNOWN
Classifier: Development Status :: 3 - Alpha
Classifier: Framework :: Pylons
Classifier: Intended Audience :: Developers
Classifier: License :: OSI Approved :: MIT License
Classifier: Programming Language :: Python :: 2.6
Classifier: Programming Language :: Python :: 2.7
